{
    "dnd5e-spellpoints.poptitle": "5e法术值系统配置",
    "dnd5e-spellpoints.form": "点击按钮打开5e法术值系统配置",
    "dnd5e-spellpoints.form-hint": "在这里，你可以配置模组行为、法术值消耗等。",
    "dnd5e-spellpoints.form-title": "法术值配置",
    "dnd5e-spellpoints.resourceLabel": "法术值资源",
    "dnd5e-spellpoints.resourceNote": "这是玩家角色表中代表法术值的资源名称（默认为：Spell Points）。",
    "dnd5e-spellpoints.mixedLabel": "启用混合模式",
    "dnd5e-spellpoints.mixedMode": "启用混合模式后，每个角色都将获得直接在角色表中启用法术值的选项。",
    "dnd5e-spellpoints.autoLabel": "启用自动法术值计算功能",
    "dnd5e-spellpoints.autoNote": "如果希望每次玩家角色晋升等级时，模组都能为你进行计算法术值，请启用此设置。",
    "dnd5e-spellpoints.formulaLabel": "法术值自动计算公式",
    "dnd5e-spellpoints.formulaNote": "该模组应使用什么公式计算 PC 法术值上限（默认值：DMG）。",
    "dnd5e-spellpoints.formulaNote2": "选择高级法术（自制），法术值将根据免费的自制模组 高级法术--法术值系统计算。",
    "dnd5e-spellpoints.AMLinkLabel": "地下城主指南网站",
    "dnd5e-spellpoints.DMG": "地下城主指南",
    "dnd5e-spellpoints.AM": "高级魔法（自制）",
    "dnd5e-spellpoints.CUSTOM": "自定义公式",
    "dnd5e-spellpoints.DMG_CUSTOM": "地下城主指南(自定义)",
    "dnd5e-spellpoints.AM_CUSTOM": "高级魔法(自定义)",
    "dnd5e-spellpoints.spellPointsCostsTitle": "法术值消耗",
    "dnd5e-spellpoints.costLabel": " {slotLevel} 环阶的法术值消耗。",
    "dnd5e-spellpoints.spellPointsCostsNote": "如果使用 DMG 上的默认法术值规则，则无需更改法术值费用",
    "dnd5e-spellpoints.AMTitle": "高级法术 - 5e 法术值系统",
    "dnd5e-spellpoints.AMNotes": "自制设置",
    "dnd5e-spellpoints.AMInstructions": "该模组允许您自定义法术值消耗，并启用默认规则中未使用的其他选项。你可以在以下网站找到免费的替代系统",
    "dnd5e-spellpoints.AMInstructions2": "你在下面看到的选项是该模组中解释的规则的一部分。",
    "dnd5e-spellpoints.enableVariantLabel": "将 HP 用作法术值（变体）",
    "dnd5e-spellpoints.enableVariantNote": "启用此功能后，玩家的角色将能够在法术值耗尽后继续施法，并以更高的成本使用自己的生命值（参见高级魔法系统）。",
    "dnd5e-spellpoints.spLifeCostLabel": "HP 多重消耗（变体）",
    "dnd5e-spellpoints.spLifeCostNote": "角色使用自己的生命施法时，最多会损失多少点生命值。这是一个乘数。例如：如果设置为 2，角色在施法时消耗 2 点法术值，最多会损失 4 点生命值（默认值：2）。",
    "dnd5e-spellpoints.use-spellpoints": "该角色使用法术值",
    "dnd5e-spellpoints.createNewResource": "请创建一个名为 {SpellPoints} 的新资源。",
    "dnd5e-spellpoints.actorNoSP": "{ActorName}已没有任何法术值",
    "dnd5e-spellpoints.castedLifeDead": "{ActorName} 使用自己的生命进行施法时，生命值上限为 0，并永久死亡！",
    "dnd5e-spellpoints.castedLife": "{ActorName}使用自己的生命值施法，损失 {hpMaxLost} 最大生命值",
    "dnd5e-spellpoints.notEnoughSp": "{ActorName} 没有足够的法术值来施放此法术。",
    "dnd5e-spellpoints.pleaseCreate": "请创建一个名为{SpellPoints}的资源来施展法术。",
    "dnd5e-spellpoints.youNotEnough": "你没有足够的{SpellPoints}来施放这个法术。",
    "dnd5e-spellpoints.spellCost": "消耗 {amount} 法术值",
    "dnd5e-spellpoints.spellUsingSpellPoints": "{ActorName}使用 {spellPointUsed}点法术值施放了一个法术。剩余{remainingPoints}点法术值。",
    "dnd5e-spellpoints.save": "保存",
    "dnd5e-spellpoints.reset": "重置",
    "dnd5e-spellpoints.spellPointsFormula": "最大法术值计算公式",
    "dnd5e-spellpoints.formulaBaseLabel": "基本公式",
    "dnd5e-spellpoints.formulaSlotLabel": "法术位公式",
    "dnd5e-spellpoints.formulaBaseNote": "如果角色至少有一个法术位，则会加上基础公式。",
    "dnd5e-spellpoints.formulaSlotNote": "法术位公式乘以角色本来拥有环阶的总法术值消耗。",
    "dnd5e-spellpoints.warlockUseSpLabel": "契术师使用法术值",
    "dnd5e-spellpoints.warlockUseSpNote": "默认情况下，契术师不能使用法术值系统，启用后他们就能像其他施法者一样使用法术值系统了。",
    "dnd5e-spellpoints.chatMessagePrivateLabel": "私人法术值使用信息。",
    "dnd5e-spellpoints.chatMessagePrivateNote": "启用此设置后，关于已使用多少法术值的聊天信息将只显示给 GM 和当前玩家，其他玩家将看不到该信息。"
}