{"DF_ARCHITECT":{"ModName":"Dragon Flagon Architect","ErrorColourSettingsMissing":"DF Architect: 'lib - ColorSettings' module required. Please install and activate 'lib - ColorSettings'","ErrorLibWrapperMissing":"DF Architect: 'libWrapper' module required. Please install and activate 'libWrapper'.","General":{"Cancel":"取消","ShowCounterName":"显示对象计数器","ShowCounterHint":"在图块、墙壁、灯光和声音层上显示对象计数器"},"ReloadRequired":{"Title":"需要重新加载","Content":"<p>需要重新加载才能使更改生效。</p>","Positive":"立即重新加载","Negative":"我要自己重新加载"},"LayerShortcuts.Settings":{"Description":"在画布图层之间切换的快捷方式。","Reset":"重置为默认值","Save":"保存","Layer":{"Tokens":"Tokens: ","Measure":"测量: ","Tiles":"图块: ","Drawings":"绘制: ","Walls":"墙: ","Lighting":"灯光: ","Sounds":"音效: ","Notes":"笔记: "},"QuickSwap":{"Title":"图层快速交换","Info":"该热键用于在两个预设图层之间快速切换。每次按下时，它都会切换到不在其上的图层。如果您所在的图层不在这对热键中，则会切换到图层 1。","Layer1_Name":"快速交换图层 1","Layer1_Hint":"按下快速交换热键时将交换的两个图层之一。","Layer2_Name":"快速交换图层 2","Layer2_Hint":"当按下快速交换热键时，将在两个图层之间交换的第二个图层。"}},"WallShortcuts.Settings":{"Description":"指定热键在不同墙体类型之间切换","ToggleForceSnapName":"切换强制捕捉到网格","ToggleForceSnapHint":"在墙面图层上切换强制捕捉到网格选项。"},"AltGridSnap":{"Label":"交替网格捕捉","Hotkey_Toggle":"切换交替网格捕捉","Setting":{"EnabledName":"显示切换交替网格捕捉","EnabledHint":"显示切换按钮，以启用交替网格捕捉到方框中心而非四角。","PlaceOnControlBarName":"放在主控制栏上","PlaceOnControlBarHint":"将交替网格捕捉切换按钮放在主控制栏上，而不是工具栏上。"}},"WallCtrlInvert":{"Title":"锁定墙链接","Name":"切换锁定墙链接","Hotkey":"切换链接锁定: "},"WallJoinSplit":{"Split_Label":"将选定的墙壁分别分割成两面墙","Join_Label":"将选中的墙线合并为一面墙"},"WallGapFiller":{"SettingName":"填墙间隙距离","SettingHint":"墙壁间隙填充功能连接两个墙壁端点所需的最大距离","ToolButtonLabel":"查找墙壁缝隙","DetectGapsLabel":"检测墙壁缝隙...","NoGaps":"未发现缺口","DialogTitle":"间隙检测","GapsDetected":"检测到 {count} 间隙。您希望关闭它们吗？","ProgressLabel":"消除间隙{0}/{1}"},"WallChangeType.Setting":{"MetaKeyName":"快速换墙键","MetaKeyHint":"点击墙壁类型控件时，您希望按住哪个键将当前选择的墙壁类型改为该墙壁类型？","MetaKey_OptionAlt":"Alt","MetaKey_OptionCtrl":"Ctrl"},"WallAltDrop.Setting":{"DistanceName":"墙端点自动捕捉","DistanceHint":"墙面端点自动捕捉当前拖动的墙面端点到相同位置所需的像素距离。"},"WallDirections.Setting":{"AllowUnselectedInvertName":"允许在未选择的墙面上反转方向","AllowUnselectedInvertHint":"允许在墙壁未被选中时使用双击右键来反转墙壁的方向。"},"AltLightOrigin.Settings":{"Colour1_Name":"灯光: 十字准线颜色","Colour1_Hint":"按住 Shift 键移动光源时显示的十字准线的颜色。","Colour2_Name":"灯光: 另一种十字准线颜色","Colour2_Hint":"移动光源时按住 Shift+Alt 时显示的十字准线的备用颜色。"},"QuickColourPicker":{"EyeDrop_Title":"从地图上选择一种颜色"},"CaptureGameScreen":{"Setting":{"AllowPC_Name":"允许玩家捕捉画布","AllowPC_Hint":"允许玩家捕捉当前游戏板画布。"},"ScreenCapture":{"Rendering":"渲染图像","Stitching":"拼接图像","ErrorStitchingFailure":"由于内存不足，无法完成图像拼接过程。您可以重试，但可能需要将场景缩小。","Background":{"Hide":"隐藏背景图片","Colour":"背景颜色","Alpha":"背景透明度"},"ShowControls":"显示控制","ShowHidden":"显示隐藏","ResetFilters":"重置过滤","Label":"保存游戏板图像","ContinueButton":"捕捉图像","Target":"您想捕捉哪一部分？","Target_Current":"当前视图","Target_All":"整个画布","Format":"选择文件格式","FormatPNG":"PNG","FormatJPG":"JPEG","FormatWEB":"WebP (Chrome Only)","Compression":"JPEG 和 WebP 的质量水平","KeepPadding":"(仅限整个画布) Include Padding","WarningNoScene":"没有正在查看的场景。请查看或激活一个场景进行画布捕捉。","WarningConfirmTitle":"超大图片","WarningConfirmContent":"<p>您正在尝试捕捉一幅非常大的图像。程序启动后，<b>不得调整</b>浏览器窗口。<br><br><i><b>不建议</b>呈现 <b>8000px x 8000px</b> 以上的内容，因为这可能会因内存限制而导致拼接失败。</i></p>"},"SaveImageDialog":{"Title":"保存图片","SaveServer":"保存在服务器上","SaveLocal":"保存在计算机上","FileNameLabel":"文件名: ","FileNamePlaceholder":"截图","DefaultFileName":"捕捉"},"ErrorCaptureInProgress":"捕捉进程已在进行中。请完成或取消后再重新尝试。"},"LightTemplate":{"CreateTemplateButton":{"LightConfig":"创建模板","MacroDirectory":"创建灯光模板"},"ContextMenu":{"Edit":"编辑模板","Remove":"移除模板","Delete":"删除模板"},"CurrentTemplate":{"Label":"当前激活模板","EditButton":"编辑模板","ExitButton":"停止放置模板"},"TemplateConfig":{"SaveButton":"保存模板","UseButton":"激活模板","ImageTitle":"灯光模板图片"},"Delete":{"Title":"删除灯光模板:","Confirm":"您确定要删除此灯光模板吗？"}},"AltLightInverted":{"InvertLuminosityButton":"将亮度反转为明暗（正值/负值）"},"TileFlattener":{"CapturePromptTitle":"平铺图块","Label":"将图块平铺成单个图像","FlattenButton":"平铺图块","RenderLighting":"Bake-In Lighting (背景不会透明)","RenderBackground":"渲染背景图像","RenderHiddenTiles":"渲染隐藏图块(仅限整个画布)","HideAnimatedTiles":"隐藏动画图块（渲染隐藏的图块必须处于关闭状态）","RenderSelectedOnly":"选定图块","RenderEntireCanvas":"整个画布","Margin":"在<b>选定图块</b>外渲染附加padding","ImageFolderTitle":"平铺图块文件夹","RenderRoofTiles":"仅渲染屋顶图块","RenderFloorTiles":"仅渲染地板图块","RenderBothTiles":"渲染地板和屋顶图块","SaveImageDialog":{"Title":"保存平铺图块","FileNameLabel":"文件名: ","FileNamePlaceholder":"tile-flattener"},"SceneReplaceDialog":{"Title":"场景更换","WhatToDo":"您希望Tile Flattener为您完成其中的任何一个过程吗？","ReplaceBackground":"替换当前场景的背景","ReplaceBackgroundHint":"当前场景的背景将更改为新创建的图像。","CloneScene":"克隆当前场景并使用图像作为背景","CloneSceneHint":"克隆当前场景及其内容，并将新场景的背景设置为新创建的图像。","ImportToScene":"导入为当前场景中的新图块","ImportToSceneHint":"将新图像作为图块导入当前场景的中心。","DoNothing":"什么都不做"}},"ShowLayerControls":{"Walls":"在其他图层上显示墙","Lights":"在其他图层上显示灯光边界","Sounds":"在其他图层上显示声音边界"},"TileConfigExt":{"LabelDimens":"图像尺寸","LabelAspect":"图像宽高比","SettingControlsName":"图块配置： 显示动画控件","SettingControlsHint":"在图块配置缩略图中显示动画的播放控件"}},"LAYERS":{"tiles":"图块层","foreground_deprecated":"前景/屋顶层","drawings":"绘图层","grid":"网格层","walls":"墙层","templates":"模板层","notes":"笔记层","tokens":"Token层","lighting":"灯光层","sounds":"音效层r","sight_deprecated":"视觉层","controls":"控制层","weather":"天气层","unknown":"\"{0} 图层\""}}