{
	"id":"zzz_mod_chn",
	"title":"Translation: 中文 [Mod]",
	"description":"本模组为 FVTT 的部分mod提供了汉化，目前的翻译基本适配于FVTT绝大多数主流mod。",
	"authors":[
		{
			"name":"记忆remix",
			"email":"1535311080@qq.com"
		}
	],
	"compatibility":{
		"minimum":"11",
		"verified":"12"
	},
	"esmodules": [
        "welcome.js"
    ],
	"languages":[
		{
			"lang":"cn",
			"name":"中文",
			"path":"cn.json"
		}
	],
	"changelog":"https://github.com/Memorize-Remix/fvtt_mod_chn/releases/tag/4.0.1",
	"version":"4.0.1",
	"url":"https://github.com/Memorize-Remix/fvtt_mod_chn",
	"manifest": "https://github.com/Memorize-Remix/fvtt_mod_chn/releases/latest/download/module.json",
	"download": "https://github.com/Memorize-Remix/fvtt_mod_chn/releases/latest/download/mod_chn.zip"
}
